{
  "_class": "rectangle",
  "booleanOperation": -1,
  "clippingMaskMode": 0,
  "do_objectID": "A7915360-B54D-4002-8AF8-D68A1EC49FC0",
  "edited": false,
  "exportOptions": {
    "_class": "exportOptions",
    "do_objectID": "4D7D86E5-9A7D-4AC4-B3BD-0D9EEFFDDA25",
    "exportFormats": [
    ],
    "includedLayerIds": [
    ],
    "layerOptions": 0,
    "shouldTrim": false
  },
  "fixedRadius": 17,
  "frame": {
    "_class": "rect",
    "constrainProportions": false,
    "do_objectID": "DBD622AE-D147-4C87-9BEF-DD3318BDD0D8",
    "height": 34,
    "width": 357,
    "x": 10,
    "y": 362
  },
  "hasClippingMask": false,
  "hasConvertedToNewRoundCorners": true,
  "isClosed": true,
  "isFixedToViewport": false,
  "isFlippedHorizontal": false,
  "isFlippedVertical": false,
  "isLocked": false,
  "isVisible": true,
  "layerListExpandedType": 1,
  "name": "Rectangle",
  "nameIsFixed": false,
  "pointRadiusBehaviour": 1,
  "points": [
    {
      "_class": "curvePoint",
      "cornerRadius": 17,
      "curveFrom": "{0, 0}",
      "curveMode": 1,
      "curveTo": "{0, 0}",
      "hasCurveFrom": false,
      "hasCurveTo": false,
      "point": "{0, 0}"
    },
    {
      "_class": "curvePoint",
      "cornerRadius": 17,
      "curveFrom": "{0.99999999999998046, 0}",
      "curveMode": 1,
      "curveTo": "{0.99999999999998046, 0}",
      "hasCurveFrom": false,
      "hasCurveTo": false,
      "point": "{0.99999999999998046, 0}"
    },
    {
      "_class": "curvePoint",
      "cornerRadius": 17,
      "curveFrom": "{0.99999999999998046, 1.0000000000000062}",
      "curveMode": 1,
      "curveTo": "{0.99999999999998046, 1.0000000000000062}",
      "hasCurveFrom": false,
      "hasCurveTo": false,
      "point": "{0.99999999999998046, 1.0000000000000062}"
    },
    {
      "_class": "curvePoint",
      "cornerRadius": 17,
      "curveFrom": "{0, 1.0000000000000062}",
      "curveMode": 1,
      "curveTo": "{0, 1.0000000000000062}",
      "hasCurveFrom": false,
      "hasCurveTo": false,
      "point": "{0, 1.0000000000000062}"
    }
  ],
  "resizingConstraint": 63,
  "resizingType": 0,
  "rotation": 0,
  "shouldBreakMaskChain": false,
  "style": {
    "_class": "style",
    "borders": [
      {
        "_class": "border",
        "color": {
          "_class": "color",
          "alpha": 1,
          "blue": 0.2902374565601349,
          "green": 0.2901752889156342,
          "red": 0.290221631526947
        },
        "fillType": 0,
        "isEnabled": true,
        "position": 1,
        "thickness": 1
      }
    ],
    "do_objectID": "C185D240-DBA9-41D3-9845-C636904C830B",
    "endMarkerType": 0,
    "fills": [
      {
        "_class": "fill",
        "color": {
          "_class": "color",
          "alpha": 1,
          "blue": 0.8627450980392157,
          "green": 0.9098039215686274,
          "red": 0.7921568627450979
        },
        "fillType": 0,
        "isEnabled": true,
        "noiseIndex": 0,
        "noiseIntensity": 0,
        "patternFillType": 1,
        "patternTileScale": 1
      }
    ],
    "miterLimit": 10,
    "startMarkerType": 0,
    "windingRule": 1
  }
}